simple/__init__.py
simple/client_context.py
simple/gateway.py
simple/merchant_credentials.py
simple/signature.py
swagger_client/__init__.py
swagger_client/api_client.py
swagger_client/configuration.py
swagger_client/rest.py
swagger_client/api/__init__.py
swagger_client/api/authentication_api.py
swagger_client/api/order_api.py
swagger_client/api/payment_api.py
swagger_client/models/__init__.py
swagger_client/models/access_token_response.py
swagger_client/models/address.py
swagger_client/models/airline.py
swagger_client/models/airline_ancillary_service_category.py
swagger_client/models/airline_travel_route.py
swagger_client/models/amount.py
swagger_client/models/amount_components.py
swagger_client/models/authentication_response_verification.py
swagger_client/models/basket_item.py
swagger_client/models/billing.py
swagger_client/models/car_rental.py
swagger_client/models/car_rental_extra_charges.py
swagger_client/models/card_verifications_transaction.py
swagger_client/models/client_locale.py
swagger_client/models/contact.py
swagger_client/models/error.py
swagger_client/models/error_details.py
swagger_client/models/error_response.py
swagger_client/models/expiration.py
swagger_client/models/frequency.py
swagger_client/models/industry_specific_extensions.py
swagger_client/models/installment_options.py
swagger_client/models/lodging.py
swagger_client/models/lodging_extra_charges.py
swagger_client/models/order.py
swagger_client/models/pay_pal.py
swagger_client/models/payment_card.py
swagger_client/models/payment_card_authentication_request.py
swagger_client/models/payment_card_authentication_result.py
swagger_client/models/payment_method.py
swagger_client/models/payment_schedules_request.py
swagger_client/models/payment_schedules_response.py
swagger_client/models/payment_url_request.py
swagger_client/models/payment_url_response.py
swagger_client/models/primary_transaction.py
swagger_client/models/primary_transaction_additional_details.py
first_data_gateway-1.0.1.dist-info/METADATA
first_data_gateway-1.0.1.dist-info/WHEEL
first_data_gateway-1.0.1.dist-info/top_level.txt
first_data_gateway-1.0.1.dist-info/RECORD
