Metadata-Version: 2.1
Name: first-data-gateway
Version: 1.0.1
Summary: First Data Gateway RESTFUL API Python SDK
Home-page: https://docs.firstdata.com/org/gateway
Author: Eric Margules
Author-email: eric.margules@firstdata.com
License: MIT
Keywords: Payment,Gateway,SDK,Developer,First Data
Platform: UNKNOWN
Requires-Dist: urllib3 (>=1.15)
Requires-Dist: six (>=1.10)
Requires-Dist: certifi
Requires-Dist: python-dateutil
